fast_unidecode-1.0.2.dist-info/METADATA
fast_unidecode-1.0.2.dist-info/WHEEL
fast_unidecode/__init__.py
fast_unidecode/fast_unidecode.cpython-310-aarch64-linux-gnu.so
fast_unidecode-1.0.2.dist-info/RECORD
