Metadata-Version: 2.4
Name: fast_unidecode
Version: 1.0.2
Summary: Provides pure ASCII transliterations of Unicode strings.
Keywords: unidecode,unidecoder,Unicode,ASCII,transliteration
Home-Page: https://github.com/stancld/rust-unidecode/
Author: Daniel Stancl <daniel.stancl@gmail.com>, Amit Chowdhury <amitc97@gmail.com>
Author-email: Daniel Stancl <daniel.stancl@gmail.com>, Amit Chowdhury <amitc97@gmail.com>
License: MIT
Project-URL: Source Code, https://github.com/stancld/rust-unidecode/
